viesvatcheck/__init__.py
viesvatcheck/client.py
viesvatcheck/countries.py
viesvatcheck/exceptions.py
viesvatcheck/util.py
viesvatcheck-0.5.0.dist-info/METADATA
viesvatcheck-0.5.0.dist-info/WHEEL
viesvatcheck-0.5.0.dist-info/RECORD
